lumin/__init__.py
lumin/data_processing/__init__.py
lumin/data_processing/file_proc.py
lumin/data_processing/hep_proc.py
lumin/data_processing/pre_proc.py
lumin/evaluation/__init__.py
lumin/evaluation/ams.py
lumin/inference/__init__.py
lumin/inference/summary_stat.py
lumin/nn/__init__.py
lumin/nn/callbacks/__init__.py
lumin/nn/callbacks/abs_callback.py
lumin/nn/callbacks/adversarial_callbacks.py
lumin/nn/callbacks/callback.py
lumin/nn/callbacks/cyclic_callbacks.py
lumin/nn/callbacks/data_callbacks.py
lumin/nn/callbacks/loss_callbacks.py
lumin/nn/callbacks/lsuv_init.py
lumin/nn/callbacks/model_callbacks.py
lumin/nn/callbacks/monitors.py
lumin/nn/callbacks/opt_callbacks.py
lumin/nn/callbacks/pred_handlers.py
lumin/nn/data/__init__.py
lumin/nn/data/batch_yielder.py
lumin/nn/data/fold_yielder.py
lumin/nn/ensemble/__init__.py
lumin/nn/ensemble/abs_ensemble.py
lumin/nn/ensemble/ensemble.py
lumin/nn/interpretation/__init__.py
lumin/nn/interpretation/features.py
lumin/nn/losses/__init__.py
lumin/nn/losses/advanced_losses.py
lumin/nn/losses/basic_weighted.py
lumin/nn/losses/hep_losses.py
lumin/nn/metrics/__init__.py
lumin/nn/metrics/class_eval.py
lumin/nn/metrics/eval_metric.py
lumin/nn/metrics/reg_eval.py
lumin/nn/models/__init__.py
lumin/nn/models/abs_model.py
lumin/nn/models/blocks/__init__.py
lumin/nn/models/blocks/abs_block.py
lumin/nn/models/blocks/body.py
lumin/nn/models/blocks/conv_blocks.py
lumin/nn/models/blocks/endcap.py
lumin/nn/models/blocks/gnn_blocks.py
lumin/nn/models/blocks/head.py
lumin/nn/models/blocks/tail.py
lumin/nn/models/helpers.py
lumin/nn/models/initialisations.py
lumin/nn/models/layers/__init__.py
lumin/nn/models/layers/activations.py
lumin/nn/models/layers/batchnorms.py
lumin/nn/models/layers/mish.py
lumin/nn/models/layers/self_attention.py
lumin/nn/models/model.py
lumin/nn/models/model_builder.py
lumin/nn/training/__init__.py
lumin/nn/training/train.py
lumin/optimisation/__init__.py
lumin/optimisation/features.py
lumin-0.9.1.dist-info/LICENSE
lumin-0.9.1.dist-info/METADATA
lumin-0.9.1.dist-info/WHEEL
lumin-0.9.1.dist-info/RECORD
