Metadata-Version: 2.1
Name: lumin
Version: 0.9.1
Summary: LUMIN Unifies Many Improvements for Networks: A PyTorch wrapper to make deep learning more accessable to scientists.
Home-page: https://mode-collaboration.github.io/
License: Apache Software License 2.0
Keywords: deep learning,differential programming,physics,science,statistics
Author: Giles Strong
Author-email: giles.c.strong@gmail.com
Requires-Python: >=3.10,<4.0
Classifier: Development Status :: 4 - Beta
Classifier: Intended Audience :: Developers
Classifier: Intended Audience :: Science/Research
Classifier: License :: OSI Approved :: Apache Software License
Classifier: License :: Other/Proprietary License
Classifier: Natural Language :: English
Classifier: Operating System :: MacOS
Classifier: Operating System :: POSIX :: Linux
Classifier: Programming Language :: Python :: 3
Classifier: Programming Language :: Python :: 3.10
Classifier: Programming Language :: Python :: 3.11
Classifier: Programming Language :: Python :: 3.12
Classifier: Programming Language :: Python :: 3.13
Requires-Dist: fastcore (>=1.0.16,<=1.3.5)
Requires-Dist: fastprogress (==0.1.21)
Requires-Dist: h5py (>=3.12.1,<4.0.0)
Requires-Dist: matplotlib (>=3.8.0,<4.0.0)
Requires-Dist: numpy (<2.0.0)
Requires-Dist: pandas (<2.1.0)
Requires-Dist: plotly (>=5.9.0)
Requires-Dist: poetry-plugin-export (>=1.8.0,<2.0.0)
Requires-Dist: prettytable (>=3.11.0,<4.0.0)
Requires-Dist: rfpimp (>=1.3.7,<2.0.0)
Requires-Dist: scikit-learn (>=1.5.2,<2.0.0)
Requires-Dist: scipy (>=1.14.1,<2.0.0)
Requires-Dist: seaborn (>=0.13.0,<0.14.0)
Requires-Dist: statsmodels (>=0.14.4,<0.15.0)
Requires-Dist: sympy (>=1.13.1,<2.0.0)
Requires-Dist: torch (>=2.5.0,<3.0.0)
Requires-Dist: torch-geometric (>=2.6.1,<3.0.0)
Requires-Dist: tqdm (>=4.66.5,<5.0.0)
Project-URL: Documentation, https://lumin.readthedocs.io/en/stable/?badge=stable
